rslv/__init__.py
rslv-0.0.0.dist-info/METADATA
rslv-0.0.0.dist-info/WHEEL
rslv-0.0.0.dist-info/RECORD
