Metadata-Version: 2.4
Name: rslv
Version: 0.0.0
Summary: Runtime Resolution
Author-email: Joel Yisrael <schizoprada@gmail.com>
Requires-Python: >=3.13
Provides-Extra: dev
Requires-Dist: black>=23.0.0; extra == 'dev'
Requires-Dist: flake8>=6.0.0; extra == 'dev'
Requires-Dist: isort>=5.12.0; extra == 'dev'
Requires-Dist: mypy>=1.0.0; extra == 'dev'
Requires-Dist: pre-commit>=3.0.0; extra == 'dev'
Requires-Dist: pytest>=7.0.0; extra == 'dev'
